{
    "id": "kaede.slug_archive",
    "name": "Slug Archive",
    "version": "0.1.0",
    "target_game_version": "v1.10.3",
    "authors": "Kaede",
    "description": "You may see this when you using this mod with one language the first time, restart the game will solve this problem.<LINE><LINE>NOTE: Please change translations in Lang folder instead of changing this line.",
    "youtube_trailer_id": "",
    "requirements": [],
    "requirements_names": [],
    "priorities": [],
    "tags": ["Game Mechanics", "Tools"],
    "checksum_override_version": false
}